{
  "configVersion": 1,
  "timestamp": 1619691292863,
  "index": "/client/gd/index.html",
  "assetGroups": [
    {
      "name": "app",
      "installMode": "prefetch",
      "updateMode": "prefetch",
      "cacheQueryOptions": {
        "ignoreVary": true
      },
      "urls": [
        "/client/gd/index.html",
        "/client/gd/manifest.webmanifest"
      ],
      "patterns": []
    },
    {
      "name": "assets",
      "installMode": "lazy",
      "updateMode": "prefetch",
      "cacheQueryOptions": {
        "ignoreVary": true
      },
      "urls": [],
      "patterns": []
    }
  ],
  "dataGroups": [],
  "hashTable": {
    "/client/gd/index.html": "db967e6a903aa48ae1a5a91cad9dc03d6936e2e5",
    "/client/gd/manifest.webmanifest": "f37cd88d260bd80e97e341096ad5c27506320827"
  },
  "navigationUrls": [
    {
      "positive": true,
      "regex": "^\\/.*$"
    },
    {
      "positive": false,
      "regex": "^\\/(?:.+\\/)?[^/]*\\.[^/]*$"
    },
    {
      "positive": false,
      "regex": "^\\/(?:.+\\/)?[^/]*__[^/]*$"
    },
    {
      "positive": false,
      "regex": "^\\/(?:.+\\/)?[^/]*__[^/]*\\/.*$"
    }
  ],
  "navigationRequestStrategy": "performance"
}